{"py/object": "rasa_core.featurizers.MaxHistoryTrackerFeaturizer", "max_history": 5, "remove_duplicates": true, "state_featurizer": {"py/object": "rasa_core.featurizers.BinarySingleStateFeaturizer", "input_state_map": {"entity_location": 81, "entity_name": 82, "intent_advice": 0, "intent_age": 1, "intent_agent_happy": 2, "intent_angry": 3, "intent_annoying": 4, "intent_answer_question": 5, "intent_are_you_sure": 6, "intent_back": 7, "intent_bad": 8, "intent_be_back": 9, "intent_beautiful": 10, "intent_birthday": 11, "intent_bored": 12, "intent_boring": 13, "intent_boss": 14, "intent_busy": 15, "intent_cant_sleep": 16, "intent_chatbot": 17, "intent_crazy": 18, "intent_doing_well": 19, "intent_dont_care": 20, "intent_excited": 21, "intent_fired": 22, "intent_friend": 23, "intent_funny": 24, "intent_go_to_bed": 25, "intent_good": 26, "intent_goodbye": 27, "intent_goodevening": 28, "intent_goodmorning": 29, "intent_goodnight": 30, "intent_greet": 31, "intent_ha_ha": 32, "intent_happy": 33, "intent_help": 34, "intent_hobby": 35, "intent_how_are_you": 36, "intent_hug": 37, "intent_hungry": 38, "intent_introduction": 39, "intent_joke": 40, "intent_lets_talk": 41, "intent_like_agent": 42, "intent_love": 43, "intent_marry": 44, "intent_miss_you": 45, "intent_my_birthday": 46, "intent_nice_to_meet": 47, "intent_nice_to_see": 48, "intent_nice_to_talk": 49, "intent_no_problem": 50, "intent_occupation": 51, "intent_origin": 52, "intent_ready": 53, "intent_real": 54, "intent_residence": 55, "intent_restaurant_search": 56, "intent_see_again": 57, "intent_smart": 58, "intent_sorry": 59, "intent_talk": 60, "intent_testing_agent": 61, "intent_thanks": 62, "intent_thankyou": 63, "intent_unhelpful": 64, "intent_user_here": 65, "intent_user_joking": 66, "intent_user_lonely": 67, "intent_user_looks_like": 68, "intent_user_sad": 69, "intent_user_sleepy": 70, "intent_user_tired": 71, "intent_user_waiting": 72, "intent_wait": 73, "intent_wanna_talk": 74, "intent_welcome": 75, "intent_well_done": 76, "intent_what_you_mean": 77, "intent_whatsup": 78, "intent_wow": 79, "intent_wrong": 80, "prev_action_deactivate_form": 88, "prev_action_default_ask_affirmation": 90, "prev_action_default_ask_rephrase": 91, "prev_action_default_fallback": 87, "prev_action_joke": 96, "prev_action_listen": 85, "prev_action_restart": 86, "prev_action_revert_fallback_events": 89, "prev_utter_goodbye": 94, "prev_utter_greet": 92, "prev_utter_searching_joke": 95, "prev_utter_unclear": 93, "slot_location_0": 83, "slot_name_0": 84}, "num_features": 97, "slot_feature_len": 2, "user_feature_len": 83}, "use_intent_probabilities": false}